{
  "jobIds": [
    "cd17202d-0a6f-48eb-b14d-1d1fa6e4a192"
  ],
  "results": [
    {
      "jobId": "cd17202d-0a6f-48eb-b14d-1d1fa6e4a192",
      "result": {
        "data": {
          "timestamp": "2024-08-14T15:11:21.95Z",
          "rootActivityId": "0df30981-d309-4ad3-8221-3c734f1c186a",
          "descriptor": {
            "Select": [
              {
                "Kind": 1,
                "Depth": 0,
                "Value": "G0",
                "GroupKeys": [
                  {
                    "Source": {
                      "Entity": "EstadoTrafico",
                      "Property": "fecha"
                    },
                    "Calc": "G0",
                    "IsSameAsSelect": true
                  }
                ],
                "Name": "EstadoTrafico.fecha"
              },
              {
                "Kind": 1,
                "Depth": 0,
                "Value": "G1",
                "Format": "0",
                "GroupKeys": [
                  {
                    "Source": {
                      "Entity": "EstadoTrafico",
                      "Property": "cant"
                    },
                    "Calc": "G1",
                    "IsSameAsSelect": true
                  }
                ],
                "Name": "Sum(EstadoTrafico.cant)"
              },
              {
                "Kind": 1,
                "Depth": 0,
                "Value": "G2",
                "GroupKeys": [
                  {
                    "Source": {
                      "Entity": "Turnos",
                      "Property": "nombre"
                    },
                    "Calc": "G2",
                    "IsSameAsSelect": true
                  }
                ],
                "Name": "Turnos.nombre"
              },
              {
                "Kind": 1,
                "Depth": 0,
                "Value": "G3",
                "Format": "\"TRUE\";\"TRUE\";\"FALSE\"",
                "GroupKeys": [
                  {
                    "Source": {
                      "Entity": "EstadoTrafico",
                      "Property": "activo"
                    },
                    "Calc": "G3",
                    "IsSameAsSelect": true
                  }
                ],
                "Name": "EstadoTrafico.activo"
              },
              {
                "Kind": 1,
                "Depth": 0,
                "Value": "G4",
                "GroupKeys": [
                  {
                    "Source": {
                      "Entity": "EstadoTrafico",
                      "Property": "mark"
                    },
                    "Calc": "G4",
                    "IsSameAsSelect": true
                  }
                ],
                "Name": "EstadoTrafico.mark"
              },
              {
                "Kind": 1,
                "Depth": 0,
                "Value": "G5",
                "GroupKeys": [
                  {
                    "Source": {
                      "Entity": "EstadoTrafico",
                      "Property": "diaSemana"
                    },
                    "Calc": "G5",
                    "IsSameAsSelect": true
                  }
                ],
                "Name": "EstadoTrafico.diaSemana"
              },
              {
                "Kind": 1,
                "Depth": 0,
                "Value": "G6",
                "GroupKeys": [
                  {
                    "Source": {
                      "Entity": "EstadoTrafico",
                      "Property": "periodo"
                    },
                    "Calc": "G6",
                    "IsSameAsSelect": true
                  }
                ],
                "Name": "EstadoTrafico.periodo"
              },
              {
                "Kind": 1,
                "Depth": 0,
                "Value": "G7",
                "GroupKeys": [
                  {
                    "Source": {
                      "Entity": "EstadoTrafico",
                      "Property": "intervaloSegmento"
                    },
                    "Calc": "G7",
                    "IsSameAsSelect": true
                  }
                ],
                "Name": "EstadoTrafico.intervaloSegmento"
              }
            ],
            "Expressions": {
              "Primary": {
                "Groupings": [
                  {
                    "Keys": [
                      {
                        "Source": {
                          "Entity": "EstadoTrafico",
                          "Property": "fecha"
                        },
                        "Select": 0
                      },
                      {
                        "Source": {
                          "Entity": "EstadoTrafico",
                          "Property": "cant"
                        },
                        "Select": 1
                      },
                      {
                        "Source": {
                          "Entity": "Turnos",
                          "Property": "nombre"
                        },
                        "Select": 2
                      },
                      {
                        "Source": {
                          "Entity": "EstadoTrafico",
                          "Property": "activo"
                        },
                        "Select": 3
                      },
                      {
                        "Source": {
                          "Entity": "EstadoTrafico",
                          "Property": "mark"
                        },
                        "Select": 4
                      },
                      {
                        "Source": {
                          "Entity": "EstadoTrafico",
                          "Property": "diaSemana"
                        },
                        "Select": 5
                      },
                      {
                        "Source": {
                          "Entity": "EstadoTrafico",
                          "Property": "periodo"
                        },
                        "Select": 6
                      },
                      {
                        "Source": {
                          "Entity": "EstadoTrafico",
                          "Property": "intervaloSegmento"
                        },
                        "Select": 7
                      }
                    ],
                    "Member": "DM0"
                  }
                ]
              }
            },
            "Limits": {
              "Primary": {
                "Id": "L0",
                "Top": {
                  "Count": 1000
                }
              }
            },
            "Version": 2
          },
          "metrics": {
            "Version": "1.0.0",
            "Events": [
              {
                "Id": "528c3e1f-d08c-4a08-b032-f1e4eb7c4a8b",
                "Name": "Execute Semantic Query",
                "Component": "DSE",
                "Start": "2024-08-14T15:11:21.9502037Z",
                "End": "2024-08-14T15:11:21.9970727Z"
              },
              {
                "Id": "89df60fe-0d1b-4c17-b3d6-7a2421467500",
                "ParentId": "528c3e1f-d08c-4a08-b032-f1e4eb7c4a8b",
                "Name": "Execute DAX Query",
                "Component": "DSE",
                "Start": "2024-08-14T15:11:21.9658794Z",
                "End": "2024-08-14T15:11:21.9970727Z",
                "Metrics": {
                  "RowCount": 0
                }
              },
              {
                "Id": "EB28567D-0AF7-4F59-BB6A-8CD4249A60A9",
                "ParentId": "89df60fe-0d1b-4c17-b3d6-7a2421467500",
                "Name": "Execute Query",
                "Component": "AS",
                "Start": "2024-08-14T15:11:21.987Z",
                "End": "2024-08-14T15:11:22.007Z"
              },
              {
                "Id": "18A0288F-49FF-4887-A1DC-6F9AA2570A82",
                "ParentId": "EB28567D-0AF7-4F59-BB6A-8CD4249A60A9",
                "Name": "Serialize Rowset",
                "Component": "AS",
                "Start": "2024-08-14T15:11:22.003Z",
                "End": "2024-08-14T15:11:22.007Z"
              }
            ]
          },
          "fromCache": false,
          "dsr": {
            "Version": 2,
            "MinorVersion": 1,
            "DS": [
              {
                "N": "DS0",
                "PH": [
                  {
                    "DM0": []
                  }
                ],
                "IC": true,
                "HAD": true
              }
            ]
          }
        }
      }
    }
  ]
}